ipg_cli/__init__.py
ipg_cli/cli.py
ipg_cli/main.py
ipg_cli/bin/__init__.py
ipg_cli/bin/test
ipg_cli/include/__init__.py
ipg_cli/lib/__init__.py
ipg_cli-0.0.1.dist-info/licenses/LICENSE
ipg_cli-0.0.1.dist-info/METADATA
ipg_cli-0.0.1.dist-info/WHEEL
ipg_cli-0.0.1.dist-info/entry_points.txt
ipg_cli-0.0.1.dist-info/top_level.txt
ipg_cli-0.0.1.dist-info/RECORD
